{"name":"02_Elofizetoi_eloszto_pont","type":"FeatureCollection"
,"features":[
{"type":"Feature","geometry":{"type":"Point","coordinates":[651897.2665,241236.5]},"properties":{"Befogado_epitmeny_tipusa":"doboz","Befogado_epitmeny_tipusa_egyeb":null,"Befogado_epitmeny_statusza":"új"}}
,{"type":"Feature","geometry":{"type":"Point","coordinates":[653064.8433,246846.7279]},"properties":{"Befogado_epitmeny_tipusa":"doboz","Befogado_epitmeny_tipusa_egyeb":null,"Befogado_epitmeny_statusza":"új"}}
,{"type":"Feature","geometry":{"type":"Point","coordinates":[655169.6991,242079.336]},"properties":{"Befogado_epitmeny_tipusa":"doboz","Befogado_epitmeny_tipusa_egyeb":null,"Befogado_epitmeny_statusza":"új"}}
,{"type":"Feature","geometry":{"type":"Point","coordinates":[656022.2934,241825.0561]},"properties":{"Befogado_epitmeny_tipusa":"doboz","Befogado_epitmeny_tipusa_egyeb":null,"Befogado_epitmeny_statusza":"új"}}
,{"type":"Feature","geometry":{"type":"Point","coordinates":[653942.3928,241409.8543]},"properties":{"Befogado_epitmeny_tipusa":"doboz","Befogado_epitmeny_tipusa_egyeb":null,"Befogado_epitmeny_statusza":"új"}}
,{"type":"Feature","geometry":{"type":"Point","coordinates":[650422.7423,239662.4274]},"properties":{"Befogado_epitmeny_tipusa":"doboz","Befogado_epitmeny_tipusa_egyeb":null,"Befogado_epitmeny_statusza":"új"}}
,{"type":"Feature","geometry":{"type":"Point","coordinates":[651580.9268,245605.5045]},"properties":{"Befogado_epitmeny_tipusa":"doboz","Befogado_epitmeny_tipusa_egyeb":null,"Befogado_epitmeny_statusza":"új"}}
,{"type":"Feature","geometry":{"type":"Point","coordinates":[652757.5013,248441.151]},"properties":{"Befogado_epitmeny_tipusa":"doboz","Befogado_epitmeny_tipusa_egyeb":null,"Befogado_epitmeny_statusza":"új"}}
,{"type":"Feature","geometry":{"type":"Point","coordinates":[654199.3646,247166.7473]},"properties":{"Befogado_epitmeny_tipusa":"doboz","Befogado_epitmeny_tipusa_egyeb":null,"Befogado_epitmeny_statusza":"új"}}
,{"type":"Feature","geometry":{"type":"Point","coordinates":[655196.2935,241529.7379]},"properties":{"Befogado_epitmeny_tipusa":"doboz","Befogado_epitmeny_tipusa_egyeb":null,"Befogado_epitmeny_statusza":"új"}}
,{"type":"Feature","geometry":{"type":"Point","coordinates":[657795.6293,240624.3745]},"properties":{"Befogado_epitmeny_tipusa":"doboz","Befogado_epitmeny_tipusa_egyeb":null,"Befogado_epitmeny_statusza":"új"}}
,{"type":"Feature","geometry":{"type":"Point","coordinates":[651195.2133,241756.3379]},"properties":{"Befogado_epitmeny_tipusa":"doboz","Befogado_epitmeny_tipusa_egyeb":null,"Befogado_epitmeny_statusza":"új"}}
,{"type":"Feature","geometry":{"type":"Point","coordinates":[651101.1326,239451.2016]},"properties":{"Befogado_epitmeny_tipusa":"doboz","Befogado_epitmeny_tipusa_egyeb":null,"Befogado_epitmeny_statusza":"új"}}
,{"type":"Feature","geometry":{"type":"Point","coordinates":[650562.8469,241999.5214]},"properties":{"Befogado_epitmeny_tipusa":"doboz","Befogado_epitmeny_tipusa_egyeb":null,"Befogado_epitmeny_statusza":"új"}}
,{"type":"Feature","geometry":{"type":"Point","coordinates":[652231.7713,243991.6877]},"properties":{"Befogado_epitmeny_tipusa":"doboz","Befogado_epitmeny_tipusa_egyeb":null,"Befogado_epitmeny_statusza":"új"}}
,{"type":"Feature","geometry":{"type":"Point","coordinates":[651357.78,243697.4669]},"properties":{"Befogado_epitmeny_tipusa":"doboz","Befogado_epitmeny_tipusa_egyeb":null,"Befogado_epitmeny_statusza":"új"}}
,{"type":"Feature","geometry":{"type":"Point","coordinates":[651841.4772,244593.8084]},"properties":{"Befogado_epitmeny_tipusa":"doboz","Befogado_epitmeny_tipusa_egyeb":null,"Befogado_epitmeny_statusza":"új"}}
,{"type":"Feature","geometry":{"type":"Point","coordinates":[653905.6433,248376.9776]},"properties":{"Befogado_epitmeny_tipusa":"doboz","Befogado_epitmeny_tipusa_egyeb":null,"Befogado_epitmeny_statusza":"új"}}
,{"type":"Feature","geometry":{"type":"Point","coordinates":[652643.1917,245208.8266]},"properties":{"Befogado_epitmeny_tipusa":"doboz","Befogado_epitmeny_tipusa_egyeb":null,"Befogado_epitmeny_statusza":"új"}}
,{"type":"Feature","geometry":{"type":"Point","coordinates":[653125.6006,247717.1047]},"properties":{"Befogado_epitmeny_tipusa":"doboz","Befogado_epitmeny_tipusa_egyeb":null,"Befogado_epitmeny_statusza":"új"}}
,{"type":"Feature","geometry":{"type":"Point","coordinates":[657476.3887,244558.8928]},"properties":{"Befogado_epitmeny_tipusa":"doboz","Befogado_epitmeny_tipusa_egyeb":null,"Befogado_epitmeny_statusza":"új"}}
,{"type":"Feature","geometry":{"type":"Point","coordinates":[656128.0398,247963.7918]},"properties":{"Befogado_epitmeny_tipusa":"doboz","Befogado_epitmeny_tipusa_egyeb":null,"Befogado_epitmeny_statusza":"új"}}
,{"type":"Feature","geometry":{"type":"Point","coordinates":[651059.296,242379.6518]},"properties":{"Befogado_epitmeny_tipusa":"doboz","Befogado_epitmeny_tipusa_egyeb":null,"Befogado_epitmeny_statusza":"új"}}
,{"type":"Feature","geometry":{"type":"Point","coordinates":[653999.1028,240842.538]},"properties":{"Befogado_epitmeny_tipusa":"doboz","Befogado_epitmeny_tipusa_egyeb":null,"Befogado_epitmeny_statusza":"új"}}
,{"type":"Feature","geometry":{"type":"Point","coordinates":[654603.447,239904.7205]},"properties":{"Befogado_epitmeny_tipusa":"doboz","Befogado_epitmeny_tipusa_egyeb":null,"Befogado_epitmeny_statusza":"új"}}
,{"type":"Feature","geometry":{"type":"Point","coordinates":[651823.3857,243122.7308]},"properties":{"Befogado_epitmeny_tipusa":"doboz","Befogado_epitmeny_tipusa_egyeb":null,"Befogado_epitmeny_statusza":"új"}}
,{"type":"Feature","geometry":{"type":"Point","coordinates":[653765.0374,246261.3982]},"properties":{"Befogado_epitmeny_tipusa":"doboz","Befogado_epitmeny_tipusa_egyeb":null,"Befogado_epitmeny_statusza":"új"}}
,{"type":"Feature","geometry":{"type":"Point","coordinates":[650196.7939,241357.0372]},"properties":{"Befogado_epitmeny_tipusa":"doboz","Befogado_epitmeny_tipusa_egyeb":null,"Befogado_epitmeny_statusza":"új"}}
,{"type":"Feature","geometry":{"type":"Point","coordinates":[657085.1921,243273.1634]},"properties":{"Befogado_epitmeny_tipusa":"doboz","Befogado_epitmeny_tipusa_egyeb":null,"Befogado_epitmeny_statusza":"új"}}
,{"type":"Feature","geometry":{"type":"Point","coordinates":[653737.4536,240309.6954]},"properties":{"Befogado_epitmeny_tipusa":"doboz","Befogado_epitmeny_tipusa_egyeb":null,"Befogado_epitmeny_statusza":"új"}}
,{"type":"Feature","geometry":{"type":"Point","coordinates":[654536.9518,241871.5356]},"properties":{"Befogado_epitmeny_tipusa":"doboz","Befogado_epitmeny_tipusa_egyeb":null,"Befogado_epitmeny_statusza":"új"}}
,{"type":"Feature","geometry":{"type":"Point","coordinates":[652772.4009,247203.6628]},"properties":{"Befogado_epitmeny_tipusa":"doboz","Befogado_epitmeny_tipusa_egyeb":null,"Befogado_epitmeny_statusza":"új"}}
,{"type":"Feature","geometry":{"type":"Point","coordinates":[653888.5747,247273.3833]},"properties":{"Befogado_epitmeny_tipusa":"doboz","Befogado_epitmeny_tipusa_egyeb":null,"Befogado_epitmeny_statusza":"új"}}
,{"type":"Feature","geometry":{"type":"Point","coordinates":[654561.5256,248306.4936]},"properties":{"Befogado_epitmeny_tipusa":"doboz","Befogado_epitmeny_tipusa_egyeb":null,"Befogado_epitmeny_statusza":"új"}}
,{"type":"Feature","geometry":{"type":"Point","coordinates":[654319.0101,240305.4665]},"properties":{"Befogado_epitmeny_tipusa":"doboz","Befogado_epitmeny_tipusa_egyeb":null,"Befogado_epitmeny_statusza":"új"}}
,{"type":"Feature","geometry":{"type":"Point","coordinates":[654160.0024,246687.3863]},"properties":{"Befogado_epitmeny_tipusa":"doboz","Befogado_epitmeny_tipusa_egyeb":null,"Befogado_epitmeny_statusza":"új"}}
,{"type":"Feature","geometry":{"type":"Point","coordinates":[650217.81,240806.6221]},"properties":{"Befogado_epitmeny_tipusa":"doboz","Befogado_epitmeny_tipusa_egyeb":null,"Befogado_epitmeny_statusza":"új"}}
,{"type":"Feature","geometry":{"type":"Point","coordinates":[652557.4606,247749.7408]},"properties":{"Befogado_epitmeny_tipusa":"doboz","Befogado_epitmeny_tipusa_egyeb":null,"Befogado_epitmeny_statusza":"új"}}
,{"type":"Feature","geometry":{"type":"Point","coordinates":[652376.2451,239751.6078]},"properties":{"Befogado_epitmeny_tipusa":"doboz","Befogado_epitmeny_tipusa_egyeb":null,"Befogado_epitmeny_statusza":"új"}}
,{"type":"Feature","geometry":{"type":"Point","coordinates":[654550.9628,247521.6808]},"properties":{"Befogado_epitmeny_tipusa":"doboz","Befogado_epitmeny_tipusa_egyeb":null,"Befogado_epitmeny_statusza":"új"}}
,{"type":"Feature","geometry":{"type":"Point","coordinates":[652991.7882,244019.1526]},"properties":{"Befogado_epitmeny_tipusa":"doboz","Befogado_epitmeny_tipusa_egyeb":null,"Befogado_epitmeny_statusza":"új"}}
,{"type":"Feature","geometry":{"type":"Point","coordinates":[653239.1973,250331.1301]},"properties":{"Befogado_epitmeny_tipusa":"doboz","Befogado_epitmeny_tipusa_egyeb":null,"Befogado_epitmeny_statusza":"új"}}
,{"type":"Feature","geometry":{"type":"Point","coordinates":[656777.5288,245162.0142]},"properties":{"Befogado_epitmeny_tipusa":"doboz","Befogado_epitmeny_tipusa_egyeb":null,"Befogado_epitmeny_statusza":"új"}}
,{"type":"Feature","geometry":{"type":"Point","coordinates":[654554.1868,244922.0556]},"properties":{"Befogado_epitmeny_tipusa":"doboz","Befogado_epitmeny_tipusa_egyeb":null,"Befogado_epitmeny_statusza":"új"}}
,{"type":"Feature","geometry":{"type":"Point","coordinates":[654974.1713,249169.9222]},"properties":{"Befogado_epitmeny_tipusa":"doboz","Befogado_epitmeny_tipusa_egyeb":null,"Befogado_epitmeny_statusza":"új"}}
,{"type":"Feature","geometry":{"type":"Point","coordinates":[653447.9027,248187.1258]},"properties":{"Befogado_epitmeny_tipusa":"doboz","Befogado_epitmeny_tipusa_egyeb":null,"Befogado_epitmeny_statusza":"új"}}
,{"type":"Feature","geometry":{"type":"Point","coordinates":[653864.1408,242700.9053]},"properties":{"Befogado_epitmeny_tipusa":"doboz","Befogado_epitmeny_tipusa_egyeb":null,"Befogado_epitmeny_statusza":"új"}}
,{"type":"Feature","geometry":{"type":"Point","coordinates":[655505.9011,244004.43]},"properties":{"Befogado_epitmeny_tipusa":"doboz","Befogado_epitmeny_tipusa_egyeb":null,"Befogado_epitmeny_statusza":"új"}}
,{"type":"Feature","geometry":{"type":"Point","coordinates":[652751.2743,244249.9941]},"properties":{"Befogado_epitmeny_tipusa":"doboz","Befogado_epitmeny_tipusa_egyeb":null,"Befogado_epitmeny_statusza":"új"}}
,{"type":"Feature","geometry":{"type":"Point","coordinates":[656708.9218,240218.8456]},"properties":{"Befogado_epitmeny_tipusa":"doboz","Befogado_epitmeny_tipusa_egyeb":null,"Befogado_epitmeny_statusza":"új"}}
,{"type":"Feature","geometry":{"type":"Point","coordinates":[650578.4086,240324.6735]},"properties":{"Befogado_epitmeny_tipusa":"doboz","Befogado_epitmeny_tipusa_egyeb":null,"Befogado_epitmeny_statusza":"új"}}
,{"type":"Feature","geometry":{"type":"Point","coordinates":[652362.314,241268.9707]},"properties":{"Befogado_epitmeny_tipusa":"doboz","Befogado_epitmeny_tipusa_egyeb":null,"Befogado_epitmeny_statusza":"új"}}
,{"type":"Feature","geometry":{"type":"Point","coordinates":[653630.4924,241628.464]},"properties":{"Befogado_epitmeny_tipusa":"doboz","Befogado_epitmeny_tipusa_egyeb":null,"Befogado_epitmeny_statusza":"új"}}
,{"type":"Feature","geometry":{"type":"Point","coordinates":[657129.6134,242194.4971]},"properties":{"Befogado_epitmeny_tipusa":"doboz","Befogado_epitmeny_tipusa_egyeb":null,"Befogado_epitmeny_statusza":"új"}}
,{"type":"Feature","geometry":{"type":"Point","coordinates":[651660.0074,239153.8222]},"properties":{"Befogado_epitmeny_tipusa":"doboz","Befogado_epitmeny_tipusa_egyeb":null,"Befogado_epitmeny_statusza":"új"}}
,{"type":"Feature","geometry":{"type":"Point","coordinates":[650782.2352,242638.2238]},"properties":{"Befogado_epitmeny_tipusa":"doboz","Befogado_epitmeny_tipusa_egyeb":null,"Befogado_epitmeny_statusza":"új"}}
,{"type":"Feature","geometry":{"type":"Point","coordinates":[655921.884,248505.644]},"properties":{"Befogado_epitmeny_tipusa":"doboz","Befogado_epitmeny_tipusa_egyeb":null,"Befogado_epitmeny_statusza":"új"}}
,{"type":"Feature","geometry":{"type":"Point","coordinates":[653608.92,244426.9054]},"properties":{"Befogado_epitmeny_tipusa":"doboz","Befogado_epitmeny_tipusa_egyeb":null,"Befogado_epitmeny_statusza":"új"}}
,{"type":"Feature","geometry":{"type":"Point","coordinates":[650795.5778,241596.551]},"properties":{"Befogado_epitmeny_tipusa":"doboz","Befogado_epitmeny_tipusa_egyeb":null,"Befogado_epitmeny_statusza":"új"}}
,{"type":"Feature","geometry":{"type":"Point","coordinates":[652474.7319,242026.5406]},"properties":{"Befogado_epitmeny_tipusa":"doboz","Befogado_epitmeny_tipusa_egyeb":null,"Befogado_epitmeny_statusza":"új"}}
,{"type":"Feature","geometry":{"type":"Point","coordinates":[655133.5682,240891.956]},"properties":{"Befogado_epitmeny_tipusa":"doboz","Befogado_epitmeny_tipusa_egyeb":null,"Befogado_epitmeny_statusza":"új"}}
,{"type":"Feature","geometry":{"type":"Point","coordinates":[653351.0014,247550.6933]},"properties":{"Befogado_epitmeny_tipusa":"doboz","Befogado_epitmeny_tipusa_egyeb":null,"Befogado_epitmeny_statusza":"új"}}
,{"type":"Feature","geometry":{"type":"Point","coordinates":[655945.5687,247139.8384]},"properties":{"Befogado_epitmeny_tipusa":"doboz","Befogado_epitmeny_tipusa_egyeb":null,"Befogado_epitmeny_statusza":"új"}}
,{"type":"Feature","geometry":{"type":"Point","coordinates":[655824.2388,242709.3161]},"properties":{"Befogado_epitmeny_tipusa":"doboz","Befogado_epitmeny_tipusa_egyeb":null,"Befogado_epitmeny_statusza":"új"}}
,{"type":"Feature","geometry":{"type":"Point","coordinates":[651425.7195,243154.8359]},"properties":{"Befogado_epitmeny_tipusa":"doboz","Befogado_epitmeny_tipusa_egyeb":null,"Befogado_epitmeny_statusza":"új"}}
,{"type":"Feature","geometry":{"type":"Point","coordinates":[654098.9559,242057.7871]},"properties":{"Befogado_epitmeny_tipusa":"doboz","Befogado_epitmeny_tipusa_egyeb":null,"Befogado_epitmeny_statusza":"új"}}
,{"type":"Feature","geometry":{"type":"Point","coordinates":[653552.8777,249132.1159]},"properties":{"Befogado_epitmeny_tipusa":"doboz","Befogado_epitmeny_tipusa_egyeb":null,"Befogado_epitmeny_statusza":"új"}}
,{"type":"Feature","geometry":{"type":"Point","coordinates":[652971.6538,239898.3422]},"properties":{"Befogado_epitmeny_tipusa":"doboz","Befogado_epitmeny_tipusa_egyeb":null,"Befogado_epitmeny_statusza":"új"}}
,{"type":"Feature","geometry":{"type":"Point","coordinates":[650863.412,239106.5895]},"properties":{"Befogado_epitmeny_tipusa":"doboz","Befogado_epitmeny_tipusa_egyeb":null,"Befogado_epitmeny_statusza":"új"}}
,{"type":"Feature","geometry":{"type":"Point","coordinates":[652236.0173,244993.2184]},"properties":{"Befogado_epitmeny_tipusa":"doboz","Befogado_epitmeny_tipusa_egyeb":null,"Befogado_epitmeny_statusza":"új"}}
,{"type":"Feature","geometry":{"type":"Point","coordinates":[653902.3635,243210.5073]},"properties":{"Befogado_epitmeny_tipusa":"doboz","Befogado_epitmeny_tipusa_egyeb":null,"Befogado_epitmeny_statusza":"új"}}
,{"type":"Feature","geometry":{"type":"Point","coordinates":[657610.6012,240949.285]},"properties":{"Befogado_epitmeny_tipusa":"doboz","Befogado_epitmeny_tipusa_egyeb":null,"Befogado_epitmeny_statusza":"új"}}
,{"type":"Feature","geometry":{"type":"Point","coordinates":[655477.3127,243165.6767]},"properties":{"Befogado_epitmeny_tipusa":"doboz","Befogado_epitmeny_tipusa_egyeb":null,"Befogado_epitmeny_statusza":"új"}}
,{"type":"Feature","geometry":{"type":"Point","coordinates":[654583.3158,242381.8379]},"properties":{"Befogado_epitmeny_tipusa":"doboz","Befogado_epitmeny_tipusa_egyeb":null,"Befogado_epitmeny_statusza":"új"}}
,{"type":"Feature","geometry":{"type":"Point","coordinates":[653041.604,245600.1217]},"properties":{"Befogado_epitmeny_tipusa":"doboz","Befogado_epitmeny_tipusa_egyeb":null,"Befogado_epitmeny_statusza":"új"}}
,{"type":"Feature","geometry":{"type":"Point","coordinates":[651399.5895,244897.2588]},"properties":{"Befogado_epitmeny_tipusa":"doboz","Befogado_epitmeny_tipusa_egyeb":null,"Befogado_epitmeny_statusza":"új"}}
,{"type":"Feature","geometry":{"type":"Point","coordinates":[652203.639,245912.135]},"properties":{"Befogado_epitmeny_tipusa":"doboz","Befogado_epitmeny_tipusa_egyeb":null,"Befogado_epitmeny_statusza":"új"}}
,{"type":"Feature","geometry":{"type":"Point","coordinates":[654545.8481,240755.1394]},"properties":{"Befogado_epitmeny_tipusa":"doboz","Befogado_epitmeny_tipusa_egyeb":null,"Befogado_epitmeny_statusza":"új"}}
,{"type":"Feature","geometry":{"type":"Point","coordinates":[655623.1043,242020.5366]},"properties":{"Befogado_epitmeny_tipusa":"doboz","Befogado_epitmeny_tipusa_egyeb":null,"Befogado_epitmeny_statusza":"új"}}
,{"type":"Feature","geometry":{"type":"Point","coordinates":[655374.9172,250299.9958]},"properties":{"Befogado_epitmeny_tipusa":"doboz","Befogado_epitmeny_tipusa_egyeb":null,"Befogado_epitmeny_statusza":"új"}}
,{"type":"Feature","geometry":{"type":"Point","coordinates":[654266.8597,243546.2419]},"properties":{"Befogado_epitmeny_tipusa":"doboz","Befogado_epitmeny_tipusa_egyeb":null,"Befogado_epitmeny_statusza":"új"}}
,{"type":"Feature","geometry":{"type":"Point","coordinates":[655640.0589,246710.6531]},"properties":{"Befogado_epitmeny_tipusa":"doboz","Befogado_epitmeny_tipusa_egyeb":null,"Befogado_epitmeny_statusza":"új"}}
,{"type":"Feature","geometry":{"type":"Point","coordinates":[656297.6116,242733.0733]},"properties":{"Befogado_epitmeny_tipusa":"doboz","Befogado_epitmeny_tipusa_egyeb":null,"Befogado_epitmeny_statusza":"új"}}
,{"type":"Feature","geometry":{"type":"Point","coordinates":[653127.8907,244727.4648]},"properties":{"Befogado_epitmeny_tipusa":"doboz","Befogado_epitmeny_tipusa_egyeb":null,"Befogado_epitmeny_statusza":"új"}}
,{"type":"Feature","geometry":{"type":"Point","coordinates":[652466.8367,246762.5531]},"properties":{"Befogado_epitmeny_tipusa":"doboz","Befogado_epitmeny_tipusa_egyeb":null,"Befogado_epitmeny_statusza":"új"}}
,{"type":"Feature","geometry":{"type":"Point","coordinates":[653372.6311,249338.7155]},"properties":{"Befogado_epitmeny_tipusa":"doboz","Befogado_epitmeny_tipusa_egyeb":null,"Befogado_epitmeny_statusza":"új"}}
,{"type":"Feature","geometry":{"type":"Point","coordinates":[655066.0171,241931.3583]},"properties":{"Befogado_epitmeny_tipusa":"doboz","Befogado_epitmeny_tipusa_egyeb":null,"Befogado_epitmeny_statusza":"új"}}
,{"type":"Feature","geometry":{"type":"Point","coordinates":[655373.5821,242694.044]},"properties":{"Befogado_epitmeny_tipusa":"doboz","Befogado_epitmeny_tipusa_egyeb":null,"Befogado_epitmeny_statusza":"új"}}
,{"type":"Feature","geometry":{"type":"Point","coordinates":[650939.5763,239789.7452]},"properties":{"Befogado_epitmeny_tipusa":"doboz","Befogado_epitmeny_tipusa_egyeb":null,"Befogado_epitmeny_statusza":"új"}}
,{"type":"Feature","geometry":{"type":"Point","coordinates":[653108.0982,243145.0503]},"properties":{"Befogado_epitmeny_tipusa":"doboz","Befogado_epitmeny_tipusa_egyeb":null,"Befogado_epitmeny_statusza":"új"}}
,{"type":"Feature","geometry":{"type":"Point","coordinates":[652648.0345,242052.688]},"properties":{"Befogado_epitmeny_tipusa":"doboz","Befogado_epitmeny_tipusa_egyeb":null,"Befogado_epitmeny_statusza":"új"}}
,{"type":"Feature","geometry":{"type":"Point","coordinates":[654511.3206,243500.4507]},"properties":{"Befogado_epitmeny_tipusa":"doboz","Befogado_epitmeny_tipusa_egyeb":null,"Befogado_epitmeny_statusza":"új"}}
,{"type":"Feature","geometry":{"type":"Point","coordinates":[652666.5531,240068.2793]},"properties":{"Befogado_epitmeny_tipusa":"doboz","Befogado_epitmeny_tipusa_egyeb":null,"Befogado_epitmeny_statusza":"új"}}
,{"type":"Feature","geometry":{"type":"Point","coordinates":[651051.9943,238660.6722]},"properties":{"Befogado_epitmeny_tipusa":"doboz","Befogado_epitmeny_tipusa_egyeb":null,"Befogado_epitmeny_statusza":"új"}}
,{"type":"Feature","geometry":{"type":"Point","coordinates":[652725.6994,243652.5443]},"properties":{"Befogado_epitmeny_tipusa":"doboz","Befogado_epitmeny_tipusa_egyeb":null,"Befogado_epitmeny_statusza":"új"}}
,{"type":"Feature","geometry":{"type":"Point","coordinates":[655624.3267,239876.2545]},"properties":{"Befogado_epitmeny_tipusa":"doboz","Befogado_epitmeny_tipusa_egyeb":null,"Befogado_epitmeny_statusza":"új"}}
,{"type":"Feature","geometry":{"type":"Point","coordinates":[653148.6844,242349.3402]},"properties":{"Befogado_epitmeny_tipusa":"doboz","Befogado_epitmeny_tipusa_egyeb":null,"Befogado_epitmeny_statusza":"új"}}
,{"type":"Feature","geometry":{"type":"Point","coordinates":[652481.6261,242896.6408]},"properties":{"Befogado_epitmeny_tipusa":"doboz","Befogado_epitmeny_tipusa_egyeb":null,"Befogado_epitmeny_statusza":"új"}}
,{"type":"Feature","geometry":{"type":"Point","coordinates":[654128.2002,245711.8726]},"properties":{"Befogado_epitmeny_tipusa":"doboz","Befogado_epitmeny_tipusa_egyeb":null,"Befogado_epitmeny_statusza":"új"}}
,{"type":"Feature","geometry":{"type":"Point","coordinates":[657534.21,242955.6855]},"properties":{"Befogado_epitmeny_tipusa":"doboz","Befogado_epitmeny_tipusa_egyeb":null,"Befogado_epitmeny_statusza":"új"}}
,{"type":"Feature","geometry":{"type":"Point","coordinates":[654801.7637,243247.8933]},"properties":{"Befogado_epitmeny_tipusa":"doboz","Befogado_epitmeny_tipusa_egyeb":null,"Befogado_epitmeny_statusza":"új"}}
,{"type":"Feature","geometry":{"type":"Point","coordinates":[653285.343,240183.8196]},"properties":{"Befogado_epitmeny_tipusa":"doboz","Befogado_epitmeny_tipusa_egyeb":null,"Befogado_epitmeny_statusza":"új"}}
,{"type":"Feature","geometry":{"type":"Point","coordinates":[655462.7521,241508.0547]},"properties":{"Befogado_epitmeny_tipusa":"doboz","Befogado_epitmeny_tipusa_egyeb":null,"Befogado_epitmeny_statusza":"új"}}
,{"type":"Feature","geometry":{"type":"Point","coordinates":[655112.4966,244802.2992]},"properties":{"Befogado_epitmeny_tipusa":"doboz","Befogado_epitmeny_tipusa_egyeb":null,"Befogado_epitmeny_statusza":"új"}}
,{"type":"Feature","geometry":{"type":"Point","coordinates":[653602.3595,245522.9527]},"properties":{"Befogado_epitmeny_tipusa":"doboz","Befogado_epitmeny_tipusa_egyeb":null,"Befogado_epitmeny_statusza":"új"}}
,{"type":"Feature","geometry":{"type":"Point","coordinates":[657158.594,241500.7014]},"properties":{"Befogado_epitmeny_tipusa":"doboz","Befogado_epitmeny_tipusa_egyeb":null,"Befogado_epitmeny_statusza":"új"}}
,{"type":"Feature","geometry":{"type":"Point","coordinates":[654619.4591,238514.8963]},"properties":{"Befogado_epitmeny_tipusa":"doboz","Befogado_epitmeny_tipusa_egyeb":null,"Befogado_epitmeny_statusza":"új"}}
,{"type":"Feature","geometry":{"type":"Point","coordinates":[653014.8329,247555.9296]},"properties":{"Befogado_epitmeny_tipusa":"doboz","Befogado_epitmeny_tipusa_egyeb":null,"Befogado_epitmeny_statusza":"új"}}
,{"type":"Feature","geometry":{"type":"Point","coordinates":[655721.8451,240922.8206]},"properties":{"Befogado_epitmeny_tipusa":"doboz","Befogado_epitmeny_tipusa_egyeb":null,"Befogado_epitmeny_statusza":"új"}}
,{"type":"Feature","geometry":{"type":"Point","coordinates":[654581.5253,246749.0741]},"properties":{"Befogado_epitmeny_tipusa":"doboz","Befogado_epitmeny_tipusa_egyeb":null,"Befogado_epitmeny_statusza":"új"}}
,{"type":"Feature","geometry":{"type":"Point","coordinates":[657815.756,244263.2262]},"properties":{"Befogado_epitmeny_tipusa":"doboz","Befogado_epitmeny_tipusa_egyeb":null,"Befogado_epitmeny_statusza":"új"}}
,{"type":"Feature","geometry":{"type":"Point","coordinates":[654786.585,242217.4632]},"properties":{"Befogado_epitmeny_tipusa":"doboz","Befogado_epitmeny_tipusa_egyeb":null,"Befogado_epitmeny_statusza":"új"}}
,{"type":"Feature","geometry":{"type":"Point","coordinates":[655134.291,246589.7564]},"properties":{"Befogado_epitmeny_tipusa":"doboz","Befogado_epitmeny_tipusa_egyeb":null,"Befogado_epitmeny_statusza":"új"}}
,{"type":"Feature","geometry":{"type":"Point","coordinates":[652691.3075,245915.8477]},"properties":{"Befogado_epitmeny_tipusa":"doboz","Befogado_epitmeny_tipusa_egyeb":null,"Befogado_epitmeny_statusza":"új"}}
,{"type":"Feature","geometry":{"type":"Point","coordinates":[653512.8468,246733.7537]},"properties":{"Befogado_epitmeny_tipusa":"doboz","Befogado_epitmeny_tipusa_egyeb":null,"Befogado_epitmeny_statusza":"új"}}
,{"type":"Feature","geometry":{"type":"Point","coordinates":[652047.4101,240132.0027]},"properties":{"Befogado_epitmeny_tipusa":"doboz","Befogado_epitmeny_tipusa_egyeb":null,"Befogado_epitmeny_statusza":"új"}}
,{"type":"Feature","geometry":{"type":"Point","coordinates":[655206.965,244711.9108]},"properties":{"Befogado_epitmeny_tipusa":"doboz","Befogado_epitmeny_tipusa_egyeb":null,"Befogado_epitmeny_statusza":"új"}}
,{"type":"Feature","geometry":{"type":"Point","coordinates":[656637.0901,243753.3978]},"properties":{"Befogado_epitmeny_tipusa":"doboz","Befogado_epitmeny_tipusa_egyeb":null,"Befogado_epitmeny_statusza":"új"}}
,{"type":"Feature","geometry":{"type":"Point","coordinates":[655890.7503,247554.9281]},"properties":{"Befogado_epitmeny_tipusa":"doboz","Befogado_epitmeny_tipusa_egyeb":null,"Befogado_epitmeny_statusza":"új"}}
,{"type":"Feature","geometry":{"type":"Point","coordinates":[652662.5237,246371.1703]},"properties":{"Befogado_epitmeny_tipusa":"doboz","Befogado_epitmeny_tipusa_egyeb":null,"Befogado_epitmeny_statusza":"új"}}
,{"type":"Feature","geometry":{"type":"Point","coordinates":[654878.3626,248857.5868]},"properties":{"Befogado_epitmeny_tipusa":"doboz","Befogado_epitmeny_tipusa_egyeb":null,"Befogado_epitmeny_statusza":"új"}}
,{"type":"Feature","geometry":{"type":"Point","coordinates":[651157.2649,240294.6723]},"properties":{"Befogado_epitmeny_tipusa":"doboz","Befogado_epitmeny_tipusa_egyeb":null,"Befogado_epitmeny_statusza":"új"}}
,{"type":"Feature","geometry":{"type":"Point","coordinates":[654576.637,247058.0373]},"properties":{"Befogado_epitmeny_tipusa":"doboz","Befogado_epitmeny_tipusa_egyeb":null,"Befogado_epitmeny_statusza":"új"}}
,{"type":"Feature","geometry":{"type":"Point","coordinates":[651341.0463,241029.0728]},"properties":{"Befogado_epitmeny_tipusa":"doboz","Befogado_epitmeny_tipusa_egyeb":null,"Befogado_epitmeny_statusza":"új"}}
,{"type":"Feature","geometry":{"type":"Point","coordinates":[650951.4827,238742.8203]},"properties":{"Befogado_epitmeny_tipusa":"doboz","Befogado_epitmeny_tipusa_egyeb":null,"Befogado_epitmeny_statusza":"új"}}
,{"type":"Feature","geometry":{"type":"Point","coordinates":[650476.0038,240908.6989]},"properties":{"Befogado_epitmeny_tipusa":"doboz","Befogado_epitmeny_tipusa_egyeb":null,"Befogado_epitmeny_statusza":"új"}}
,{"type":"Feature","geometry":{"type":"Point","coordinates":[654790.8102,242877.2926]},"properties":{"Befogado_epitmeny_tipusa":"doboz","Befogado_epitmeny_tipusa_egyeb":null,"Befogado_epitmeny_statusza":"új"}}
,{"type":"Feature","geometry":{"type":"Point","coordinates":[654985.7353,248568.3584]},"properties":{"Befogado_epitmeny_tipusa":"doboz","Befogado_epitmeny_tipusa_egyeb":null,"Befogado_epitmeny_statusza":"új"}}
,{"type":"Feature","geometry":{"type":"Point","coordinates":[655987.9431,241469.2324]},"properties":{"Befogado_epitmeny_tipusa":"doboz","Befogado_epitmeny_tipusa_egyeb":null,"Befogado_epitmeny_statusza":"új"}}
,{"type":"Feature","geometry":{"type":"Point","coordinates":[654045.1374,247744.9598]},"properties":{"Befogado_epitmeny_tipusa":"doboz","Befogado_epitmeny_tipusa_egyeb":null,"Befogado_epitmeny_statusza":"új"}}
,{"type":"Feature","geometry":{"type":"Point","coordinates":[654462.4521,239319.6127]},"properties":{"Befogado_epitmeny_tipusa":"doboz","Befogado_epitmeny_tipusa_egyeb":null,"Befogado_epitmeny_statusza":"új"}}
,{"type":"Feature","geometry":{"type":"Point","coordinates":[652963.6149,241733.2944]},"properties":{"Befogado_epitmeny_tipusa":"doboz","Befogado_epitmeny_tipusa_egyeb":null,"Befogado_epitmeny_statusza":"új"}}
,{"type":"Feature","geometry":{"type":"Point","coordinates":[653508.2877,245746.2323]},"properties":{"Befogado_epitmeny_tipusa":"doboz","Befogado_epitmeny_tipusa_egyeb":null,"Befogado_epitmeny_statusza":"új"}}
,{"type":"Feature","geometry":{"type":"Point","coordinates":[653292.6816,246261.9543]},"properties":{"Befogado_epitmeny_tipusa":"doboz","Befogado_epitmeny_tipusa_egyeb":null,"Befogado_epitmeny_statusza":"új"}}
,{"type":"Feature","geometry":{"type":"Point","coordinates":[652237.331,247197.1031]},"properties":{"Befogado_epitmeny_tipusa":"doboz","Befogado_epitmeny_tipusa_egyeb":null,"Befogado_epitmeny_statusza":"új"}}
,{"type":"Feature","geometry":{"type":"Point","coordinates":[656294.498,244984.8808]},"properties":{"Befogado_epitmeny_tipusa":"doboz","Befogado_epitmeny_tipusa_egyeb":null,"Befogado_epitmeny_statusza":"új"}}
,{"type":"Feature","geometry":{"type":"Point","coordinates":[653023.1453,248695.3432]},"properties":{"Befogado_epitmeny_tipusa":"doboz","Befogado_epitmeny_tipusa_egyeb":null,"Befogado_epitmeny_statusza":"új"}}
,{"type":"Feature","geometry":{"type":"Point","coordinates":[653073.1831,241029.9016]},"properties":{"Befogado_epitmeny_tipusa":"doboz","Befogado_epitmeny_tipusa_egyeb":null,"Befogado_epitmeny_statusza":"új"}}
,{"type":"Feature","geometry":{"type":"Point","coordinates":[652846.5031,249226.4812]},"properties":{"Befogado_epitmeny_tipusa":"doboz","Befogado_epitmeny_tipusa_egyeb":null,"Befogado_epitmeny_statusza":"új"}}
,{"type":"Feature","geometry":{"type":"Point","coordinates":[654311.8993,242891.9717]},"properties":{"Befogado_epitmeny_tipusa":"doboz","Befogado_epitmeny_tipusa_egyeb":null,"Befogado_epitmeny_statusza":"új"}}
,{"type":"Feature","geometry":{"type":"Point","coordinates":[656866.5961,240968.6334]},"properties":{"Befogado_epitmeny_tipusa":"doboz","Befogado_epitmeny_tipusa_egyeb":null,"Befogado_epitmeny_statusza":"új"}}
,{"type":"Feature","geometry":{"type":"Point","coordinates":[654465.7881,246232.3759]},"properties":{"Befogado_epitmeny_tipusa":"doboz","Befogado_epitmeny_tipusa_egyeb":null,"Befogado_epitmeny_statusza":"új"}}
,{"type":"Feature","geometry":{"type":"Point","coordinates":[653141.0125,247207.5548]},"properties":{"Befogado_epitmeny_tipusa":"doboz","Befogado_epitmeny_tipusa_egyeb":null,"Befogado_epitmeny_statusza":"új"}}
,{"type":"Feature","geometry":{"type":"Point","coordinates":[651580.8744,242648.1395]},"properties":{"Befogado_epitmeny_tipusa":"doboz","Befogado_epitmeny_tipusa_egyeb":null,"Befogado_epitmeny_statusza":"új"}}
,{"type":"Feature","geometry":{"type":"Point","coordinates":[651957.565,240714.5529]},"properties":{"Befogado_epitmeny_tipusa":"doboz","Befogado_epitmeny_tipusa_egyeb":null,"Befogado_epitmeny_statusza":"új"}}
,{"type":"Feature","geometry":{"type":"Point","coordinates":[653243.5333,243934.0896]},"properties":{"Befogado_epitmeny_tipusa":"doboz","Befogado_epitmeny_tipusa_egyeb":null,"Befogado_epitmeny_statusza":"új"}}
,{"type":"Feature","geometry":{"type":"Point","coordinates":[654954.0444,250142.9887]},"properties":{"Befogado_epitmeny_tipusa":"doboz","Befogado_epitmeny_tipusa_egyeb":null,"Befogado_epitmeny_statusza":"új"}}
,{"type":"Feature","geometry":{"type":"Point","coordinates":[651604.7425,239314.9428]},"properties":{"Befogado_epitmeny_tipusa":"doboz","Befogado_epitmeny_tipusa_egyeb":null,"Befogado_epitmeny_statusza":"új"}}
,{"type":"Feature","geometry":{"type":"Point","coordinates":[654293.3237,248130.6953]},"properties":{"Befogado_epitmeny_tipusa":"doboz","Befogado_epitmeny_tipusa_egyeb":null,"Befogado_epitmeny_statusza":"új"}}
,{"type":"Feature","geometry":{"type":"Point","coordinates":[653666.0737,247793.2186]},"properties":{"Befogado_epitmeny_tipusa":"doboz","Befogado_epitmeny_tipusa_egyeb":null,"Befogado_epitmeny_statusza":"új"}}
,{"type":"Feature","geometry":{"type":"Point","coordinates":[656016.5108,240493.1642]},"properties":{"Befogado_epitmeny_tipusa":"doboz","Befogado_epitmeny_tipusa_egyeb":null,"Befogado_epitmeny_statusza":"új"}}
,{"type":"Feature","geometry":{"type":"Point","coordinates":[656131.7093,246515.5891]},"properties":{"Befogado_epitmeny_tipusa":"doboz","Befogado_epitmeny_tipusa_egyeb":null,"Befogado_epitmeny_statusza":"új"}}
,{"type":"Feature","geometry":{"type":"Point","coordinates":[654197.4743,242520.6908]},"properties":{"Befogado_epitmeny_tipusa":"doboz","Befogado_epitmeny_tipusa_egyeb":null,"Befogado_epitmeny_statusza":"új"}}
,{"type":"Feature","geometry":{"type":"Point","coordinates":[650064.583,240052.0544]},"properties":{"Befogado_epitmeny_tipusa":"doboz","Befogado_epitmeny_tipusa_egyeb":null,"Befogado_epitmeny_statusza":"új"}}
,{"type":"Feature","geometry":{"type":"Point","coordinates":[653917.1944,244920.4001]},"properties":{"Befogado_epitmeny_tipusa":"doboz","Befogado_epitmeny_tipusa_egyeb":null,"Befogado_epitmeny_statusza":"új"}}
,{"type":"Feature","geometry":{"type":"Point","coordinates":[657286.3737,240281.684]},"properties":{"Befogado_epitmeny_tipusa":"doboz","Befogado_epitmeny_tipusa_egyeb":null,"Befogado_epitmeny_statusza":"új"}}
,{"type":"Feature","geometry":{"type":"Point","coordinates":[650816.1949,238449.941]},"properties":{"Befogado_epitmeny_tipusa":"doboz","Befogado_epitmeny_tipusa_egyeb":null,"Befogado_epitmeny_statusza":"új"}}
,{"type":"Feature","geometry":{"type":"Point","coordinates":[657291.0264,244010.5913]},"properties":{"Befogado_epitmeny_tipusa":"doboz","Befogado_epitmeny_tipusa_egyeb":null,"Befogado_epitmeny_statusza":"új"}}
,{"type":"Feature","geometry":{"type":"Point","coordinates":[651031.1998,243151.2771]},"properties":{"Befogado_epitmeny_tipusa":"doboz","Befogado_epitmeny_tipusa_egyeb":null,"Befogado_epitmeny_statusza":"új"}}
,{"type":"Feature","geometry":{"type":"Point","coordinates":[653815.6308,242178.7667]},"properties":{"Befogado_epitmeny_tipusa":"doboz","Befogado_epitmeny_tipusa_egyeb":null,"Befogado_epitmeny_statusza":"új"}}
,{"type":"Feature","geometry":{"type":"Point","coordinates":[651559.6313,240656.4176]},"properties":{"Befogado_epitmeny_tipusa":"doboz","Befogado_epitmeny_tipusa_egyeb":null,"Befogado_epitmeny_statusza":"új"}}
,{"type":"Feature","geometry":{"type":"Point","coordinates":[654688.7168,244067.1113]},"properties":{"Befogado_epitmeny_tipusa":"doboz","Befogado_epitmeny_tipusa_egyeb":null,"Befogado_epitmeny_statusza":"új"}}
,{"type":"Feature","geometry":{"type":"Point","coordinates":[655666.1357,244266.4511]},"properties":{"Befogado_epitmeny_tipusa":"doboz","Befogado_epitmeny_tipusa_egyeb":null,"Befogado_epitmeny_statusza":"új"}}
,{"type":"Feature","geometry":{"type":"Point","coordinates":[654477.0183,241360.2623]},"properties":{"Befogado_epitmeny_tipusa":"doboz","Befogado_epitmeny_tipusa_egyeb":null,"Befogado_epitmeny_statusza":"új"}}
,{"type":"Feature","geometry":{"type":"Point","coordinates":[657383.4302,240748.2455]},"properties":{"Befogado_epitmeny_tipusa":"doboz","Befogado_epitmeny_tipusa_egyeb":null,"Befogado_epitmeny_statusza":"új"}}
,{"type":"Feature","geometry":{"type":"Point","coordinates":[651502.5276,240603.5952]},"properties":{"Befogado_epitmeny_tipusa":"doboz","Befogado_epitmeny_tipusa_egyeb":null,"Befogado_epitmeny_statusza":"új"}}
,{"type":"Feature","geometry":{"type":"Point","coordinates":[655161.5338,240490.8292]},"properties":{"Befogado_epitmeny_tipusa":"doboz","Befogado_epitmeny_tipusa_egyeb":null,"Befogado_epitmeny_statusza":"új"}}
]}
